[
  {
    "languages": [
      {
        "name": "Other",
        "total_seconds": 14533,
        "digital": "4:02:13",
        "decimal": "4.03",
        "text": "4 hrs 2 mins",
        "hours": 4,
        "minutes": 2,
        "seconds": 13,
        "percent": 100
      }
    ],
    "grand_total": {
      "hours": 4,
      "minutes": 2,
      "total_seconds": 14533,
      "digital": "4:02",
      "decimal": "4.03",
      "text": "4 hrs 2 mins"
    },
    "editors": [
      {
        "name": "Chrome",
        "total_seconds": 14533,
        "digital": "4:02:13",
        "decimal": "4.03",
        "text": "4 hrs 2 mins",
        "hours": 4,
        "minutes": 2,
        "seconds": 13,
        "percent": 100
      }
    ],
    "operating_systems": [
      {
        "name": "Windows",
        "total_seconds": 14533,
        "digital": "4:02:13",
        "decimal": "4.03",
        "text": "4 hrs 2 mins",
        "hours": 4,
        "minutes": 2,
        "seconds": 13,
        "percent": 100
      }
    ],
    "categories": [
      {
        "name": "Browsing",
        "total_seconds": 14533,
        "digital": "4:02:13",
        "decimal": "4.03",
        "text": "4 hrs 2 mins",
        "hours": 4,
        "minutes": 2,
        "seconds": 13,
        "percent": 100
      }
    ],
    "dependencies": [],
    "machines": [
      {
        "name": "Unknown Hostname",
        "total_seconds": 14533,
        "machine_name_id": "d0b1d22b-7f75-438e-a22e-31c531ce4c1f",
        "digital": "4:02:13",
        "decimal": "4.03",
        "text": "4 hrs 2 mins",
        "hours": 4,
        "minutes": 2,
        "seconds": 13,
        "percent": 100
      }
    ],
    "projects": [
      {
        "name": "uptime-kuma",
        "total_seconds": 8150,
        "digital": "2:15:50",
        "decimal": "2.25",
        "text": "2 hrs 15 mins",
        "hours": 2,
        "minutes": 15,
        "seconds": 50,
        "percent": 56.08
      },
      {
        "name": "turbo",
        "total_seconds": 2779,
        "digital": "0:46:19",
        "decimal": "0.77",
        "text": "46 mins",
        "hours": 0,
        "minutes": 46,
        "seconds": 19,
        "percent": 19.12
      },
      {
        "name": "archiver",
        "total_seconds": 1493,
        "digital": "0:24:53",
        "decimal": "0.40",
        "text": "24 mins",
        "hours": 0,
        "minutes": 24,
        "seconds": 53,
        "percent": 10.27
      },
      {
        "name": "status-page-advanced",
        "total_seconds": 926,
        "digital": "0:15:26",
        "decimal": "0.25",
        "text": "15 mins",
        "hours": 0,
        "minutes": 15,
        "seconds": 26,
        "percent": 6.37
      },
      {
        "name": "status",
        "total_seconds": 702,
        "digital": "0:11:42",
        "decimal": "0.18",
        "text": "11 mins",
        "hours": 0,
        "minutes": 11,
        "seconds": 42,
        "percent": 4.83
      },
      {
        "name": "devmirza-blog-backend",
        "total_seconds": 349,
        "digital": "0:05:49",
        "decimal": "0.08",
        "text": "5 mins",
        "hours": 0,
        "minutes": 5,
        "seconds": 49,
        "percent": 2.4
      },
      {
        "name": "ai-3d-website",
        "total_seconds": 84,
        "digital": "0:01:24",
        "decimal": "0.02",
        "text": "1 min",
        "hours": 0,
        "minutes": 1,
        "seconds": 24,
        "percent": 0.58
      },
      {
        "name": "large-monorepo",
        "total_seconds": 36,
        "digital": "0:00:36",
        "decimal": "0.00",
        "text": "36 secs",
        "hours": 0,
        "minutes": 0,
        "seconds": 36,
        "percent": 0.25
      },
      {
        "name": "oauth",
        "total_seconds": 5,
        "digital": "0:00:05",
        "decimal": "0.00",
        "text": "5 secs",
        "hours": 0,
        "minutes": 0,
        "seconds": 5,
        "percent": 0.03
      },
      {
        "name": "github_editor?redirect=%2Fvercel%2Fturbo%2Fblob%2Fmain%2F.github%2Fworkflows%2Fpr-clean-caches.yml&requestId=dd31d0eb-510e-4ee8-aeae-5dceac61986b",
        "total_seconds": 3,
        "digital": "0:00:03",
        "decimal": "0.00",
        "text": "3 secs",
        "hours": 0,
        "minutes": 0,
        "seconds": 3,
        "percent": 0.02
      },
      {
        "name": "github_editor?redirect=%2FDevMirza-Blog%2Fdevmirza-blog-backend&requestId=79ab6725-a115-4cec-83c0-bbaf49dc63d0",
        "total_seconds": 2,
        "digital": "0:00:02",
        "decimal": "0.00",
        "text": "2 secs",
        "hours": 0,
        "minutes": 0,
        "seconds": 2,
        "percent": 0.01
      },
      {
        "name": "github_editor?redirect=%2FDevMirza-Blog%2Fstatus&requestId=f73237ea-1e3d-422c-9555-751961f77bba",
        "total_seconds": 2,
        "digital": "0:00:02",
        "decimal": "0.00",
        "text": "2 secs",
        "hours": 0,
        "minutes": 0,
        "seconds": 2,
        "percent": 0.01
      },
      {
        "name": "awesome-selfhosted#games",
        "total_seconds": 1,
        "digital": "0:00:01",
        "decimal": "0.00",
        "text": "1 sec",
        "hours": 0,
        "minutes": 0,
        "seconds": 1,
        "percent": 0.01
      },
      {
        "name": "github_editor?redirect=%2FZaid-maker%2Farchiver&requestId=17fdef42-64ef-4db1-80f0-ec34792d7f0f",
        "total_seconds": 1,
        "digital": "0:00:01",
        "decimal": "0.00",
        "text": "1 sec",
        "hours": 0,
        "minutes": 0,
        "seconds": 1,
        "percent": 0.01
      }
    ],
    "range": {
      "start": "2023-06-28T19:00:00Z",
      "end": "2023-06-29T18:59:59Z",
      "date": "2023-06-29",
      "text": "Thu Jun 29th 2023",
      "timezone": "Asia/Karachi"
    }
  }
]